jaii/__init__.py
jaiii-1.0.0.dist-info/LICENSE
jaiii-1.0.0.dist-info/METADATA
jaiii-1.0.0.dist-info/WHEEL
jaiii-1.0.0.dist-info/top_level.txt
jaiii-1.0.0.dist-info/RECORD
